[
  {
    "id": 1,
    "name": "Carlos Eduardo da Silva",
    "email": "me@exemple.com",
    "password": "ola123",
    "position_id": 1,
    "created_at": "2026-02-28T14:33:30.569Z",
    "updated_at": "2026-03-01T19:00:56.338Z"
  },
  {
    "id": 2,
    "name": "Jose Almeida",
    "email": "jose@exemple.com",
    "password": "password",
    "position_id": 1,
    "created_at": "2026-02-28T14:40:56.792Z",
    "updated_at": "2026-02-28T14:40:56.792Z"
  },
  {
    "id": 3,
    "name": "Arthur de paula Correa",
    "email": "arthurdepaulacorreadev@gmail.com",
    "position_id": 1,
    "password": "ismmbbcl",
    "created_at": "2026-03-01T19:02:49.312Z",
    "updated_at": "2026-03-01T19:02:49.312Z"
  }
]
